kla_first_distributions/Binomialdistribution.py
kla_first_distributions/Gaussiandistribution.py
kla_first_distributions/Generaldistribution.py
kla_first_distributions/__init__.py
kla_first_distributions-0.86.dist-info/METADATA
kla_first_distributions-0.86.dist-info/WHEEL
kla_first_distributions-0.86.dist-info/top_level.txt
kla_first_distributions-0.86.dist-info/RECORD
