Metadata-Version: 2.1
Name: kla_first_distributions
Version: 0.86
Summary: Gaussian and Binomial distributions
Author: KA
Author-email: myemail@somthing.com
